openimis_be_workflow-1.1.0.dist-info/licenses/LICENSE.md
workflow/__init__.py
workflow/admin.py
workflow/apps.py
workflow/exceptions.py
workflow/gql_queries.py
workflow/models.py
workflow/schema.py
workflow/services.py
workflow/tests.py
workflow/urls.py
workflow/util.py
workflow/views.py
workflow/migrations/__init__.py
workflow/systems/__init__.py
workflow/systems/base/__init__.py
workflow/systems/base/adaptor.py
workflow/systems/base/handler.py
workflow/systems/lightning/__init__.py
workflow/systems/lightning/adaptor.py
workflow/systems/lightning/client.py
workflow/systems/lightning/handler.py
workflow/systems/python/__init__.py
workflow/systems/python/adaptor.py
workflow/systems/python/handler.py
openimis_be_workflow-1.1.0.dist-info/METADATA
openimis_be_workflow-1.1.0.dist-info/WHEEL
openimis_be_workflow-1.1.0.dist-info/top_level.txt
openimis_be_workflow-1.1.0.dist-info/RECORD
